{"accessibilityFocused":false,"bounds":{"bottom":2560,"left":0,"right":1600,"top":0},"checkable":false,"checked":false,"children":[{"accessibilityFocused":false,"bounds":{"bottom":2560,"left":0,"right":1600,"top":0},"checkable":false,"checked":false,"children":[{"accessibilityFocused":false,"bounds":{"bottom":2560,"left":0,"right":1600,"top":0},"checkable":false,"checked":false,"children":[{"accessibilityFocused":false,"bounds":{"bottom":2560,"left":0,"right":1600,"top":0},"checkable":false,"checked":false,"className":"android.widget.FrameLayout","clickable":false,"descendantCount":0,"dismissable":false,"editable":false,"enabled":true,"focusable":true,"focused":false,"invisibleToUser":false,"level":3,"longClickable":false,"packageName":"com.sina.weibo","password":false,"scrollable":false,"selected":false},{"accessibilityFocused":false,"bounds":{"bottom":2560,"left":0,"right":1600,"top":0},"checkable":false,"checked":false,"children":[{"accessibilityFocused":false,"bounds":{"bottom":151,"left":0,"right":1600,"top":0},"checkable":false,"checked":false,"children":[{"accessibilityFocused":false,"bounds":{"bottom":151,"left":0,"right":1600,"top":64},"checkable":false,"checked":false,"children":[{"accessibilityFocused":false,"bounds":{"bottom":151,"left":0,"right":377,"top":64},"checkable":false,"checked":false,"children":[{"accessibilityFocused":false,"bounds":{"bottom":151,"left":24,"right":88,"top":64},"checkable":false,"checked":false,"children":[{"accessibilityFocused":false,"bounds":{"bottom":129,"left":24,"right":88,"top":86},"checkable":false,"checked":false,"className":"android.widget.TextView","clickable":false,"contentDescription":"取消","descendantCount":0,"dismissable":false,"editable":false,"enabled":true,"focusable":false,"focused":false,"invisibleToUser":false,"level":8,"longClickable":false,"packageName":"com.sina.weibo","password":false,"resourceId":"com.sina.weibo:id/titleBack","scrollable":false,"selected":false,"text":"取消"}],"className":"android.widget.RelativeLayout","clickable":false,"descendantCount":1,"dismissable":false,"editable":false,"enabled":true,"focusable":false,"focused":false,"invisibleToUser":false,"level":7,"longClickable":false,"packageName":"com.sina.weibo","password":false,"resourceId":"com.sina.weibo:id/titleBackOuter","scrollable":false,"selected":false},{"accessibilityFocused":false,"bounds":{"bottom":76,"left":88,"right":88,"top":76},"checkable":false,"checked":false,"className":"android.widget.FrameLayout","clickable":false,"descendantCount":0,"dismissable":false,"editable":false,"enabled":true,"focusable":false,"focused":false,"invisibleToUser":true,"level":7,"longClickable":false,"packageName":"com.sina.weibo","password":false,"scrollable":false,"selected":false}],"className":"android.widget.LinearLayout","clickable":true,"descendantCount":3,"dismissable":false,"editable":false,"enabled":true,"focusable":false,"focused":false,"invisibleToUser":false,"level":6,"longClickable":false,"packageName":"com.sina.weibo","password":false,"resourceId":"com.sina.weibo:id/rltitleBack","scrollable":false,"selected":false},{"accessibilityFocused":false,"bounds":{"bottom":151,"left":642,"right":958,"top":64},"checkable":false,"checked":false,"children":[{"accessibilityFocused":false,"bounds":{"bottom":151,"left":642,"right":958,"top":64},"checkable":false,"checked":false,"children":[{"accessibilityFocused":false,"bounds":{"bottom":142,"left":644,"right":956,"top":72},"checkable":false,"checked":false,"children":[{"accessibilityFocused":false,"bounds":{"bottom":112,"left":749,"right":851,"top":72},"checkable":false,"checked":false,"children":[{"accessibilityFocused":false,"bounds":{"bottom":112,"left":749,"right":851,"top":72},"checkable":false,"checked":false,"className":"android.widget.TextView","clickable":false,"descendantCount":0,"dismissable":false,"editable":false,"enabled":true,"focusable":false,"focused":false,"invisibleToUser":false,"level":10,"longClickable":false,"packageName":"com.sina.weibo","password":false,"resourceId":"com.sina.weibo:id/titleText","scrollable":false,"selected":false,"text":"发微博"}],"className":"android.widget.LinearLayout","clickable":false,"descendantCount":1,"dismissable":false,"editable":false,"enabled":true,"focusable":false,"focused":false,"invisibleToUser":false,"level":9,"longClickable":false,"packageName":"com.sina.weibo","password":false,"scrollable":false,"selected":false},{"accessibilityFocused":false,"bounds":{"bottom":142,"left":644,"right":956,"top":114},"checkable":false,"checked":false,"className":"android.widget.TextView","clickable":false,"descendantCount":0,"dismissable":false,"editable":false,"enabled":true,"focusable":false,"focused":false,"invisibleToUser":false,"level":9,"longClickable":false,"packageName":"com.sina.weibo","password":false,"resourceId":"com.sina.weibo:id/subTitleText","scrollable":false,"selected":false,"text":"闵玧其放下羞涩我已经看上你"}],"className":"android.widget.LinearLayout","clickable":false,"descendantCount":3,"dismissable":false,"editable":false,"enabled":true,"focusable":false,"focused":false,"invisibleToUser":false,"level":8,"longClickable":false,"packageName":"com.sina.weibo","password":false,"scrollable":false,"selected":false}],"className":"android.widget.LinearLayout","clickable":false,"descendantCount":4,"dismissable":false,"editable":false,"enabled":true,"focusable":false,"focused":false,"invisibleToUser":false,"level":7,"longClickable":false,"packageName":"com.sina.weibo","password":false,"resourceId":"com.sina.weibo:id/ll_title","scrollable":false,"selected":false}],"className":"android.widget.RelativeLayout","clickable":false,"descendantCount":5,"dismissable":false,"editable":false,"enabled":true,"focusable":false,"focused":false,"invisibleToUser":false,"level":6,"longClickable":false,"packageName":"com.sina.weibo","password":false,"resourceId":"com.sina.weibo:id/rltitlemiddle","scrollable":false,"selected":false},{"accessibilityFocused":false,"bounds":{"bottom":151,"left":1464,"right":1600,"top":64},"checkable":false,"checked":false,"children":[{"accessibilityFocused":false,"bounds":{"bottom":151,"left":1480,"right":1576,"top":64},"checkable":false,"checked":false,"children":[{"accessibilityFocused":false,"bounds":{"bottom":138,"left":1480,"right":1576,"top":78},"checkable":false,"checked":false,"className":"android.widget.TextView","clickable":false,"contentDescription":"发送","descendantCount":0,"dismissable":false,"editable":false,"enabled":true,"focusable":false,"focused":false,"invisibleToUser":false,"level":8,"longClickable":false,"packageName":"com.sina.weibo","password":false,"resourceId":"com.sina.weibo:id/titleSave","scrollable":false,"selected":false,"text":"发送"}],"className":"android.widget.FrameLayout","clickable":false,"descendantCount":1,"dismissable":false,"editable":false,"enabled":true,"focusable":false,"focused":false,"invisibleToUser":false,"level":7,"longClickable":false,"packageName":"com.sina.weibo","password":false,"resourceId":"com.sina.weibo:id/rightBtn_wrapper","scrollable":false,"selected":false}],"className":"android.widget.LinearLayout","clickable":true,"descendantCount":2,"dismissable":false,"editable":false,"enabled":true,"focusable":false,"focused":false,"invisibleToUser":false,"level":6,"longClickable":false,"packageName":"com.sina.weibo","password":false,"resourceId":"com.sina.weibo:id/rltitleSave","scrollable":false,"selected":false}],"className":"android.widget.RelativeLayout","clickable":false,"descendantCount":13,"dismissable":false,"editable":false,"enabled":true,"focusable":false,"focused":false,"invisibleToUser":false,"level":5,"longClickable":false,"packageName":"com.sina.weibo","password":false,"resourceId":"com.sina.weibo:id/realTitleBar","scrollable":false,"selected":false}],"className":"android.widget.RelativeLayout","clickable":false,"descendantCount":14,"dismissable":false,"editable":false,"enabled":true,"focusable":false,"focused":false,"invisibleToUser":false,"level":4,"longClickable":false,"packageName":"com.sina.weibo","password":false,"resourceId":"com.sina.weibo:id/lyTitleBar","scrollable":false,"selected":false},{"accessibilityFocused":false,"bounds":{"bottom":2560,"left":0,"right":1600,"top":151},"checkable":false,"checked":false,"children":[{"accessibilityFocused":false,"bounds":{"bottom":151,"left":0,"right":1600,"top":151},"checkable":false,"checked":false,"className":"android.widget.ImageView","clickable":false,"descendantCount":0,"dismissable":false,"editable":false,"enabled":true,"focusable":false,"focused":false,"invisibleToUser":true,"level":5,"longClickable":false,"packageName":"com.sina.weibo","password":false,"scrollable":false,"selected":false},{"accessibilityFocused":false,"bounds":{"bottom":1731,"left":0,"right":1600,"top":151},"checkable":false,"checked":false,"children":[{"accessibilityFocused":false,"bounds":{"bottom":1394,"left":0,"right":1600,"top":151},"checkable":false,"checked":false,"children":[{"accessibilityFocused":false,"bounds":{"bottom":391,"left":0,"right":1600,"top":151},"checkable":false,"checked":false,"children":[{"accessibilityFocused":false,"bounds":{"bottom":391,"left":0,"right":1600,"top":151},"checkable":false,"checked":false,"children":[{"accessibilityFocused":false,"bounds":{"bottom":300,"left":30,"right":1570,"top":151},"checkable":false,"checked":false,"children":[{"accessibilityFocused":false,"bounds":{"bottom":300,"left":30,"right":1570,"top":151},"checkable":false,"checked":false,"children":[{"accessibilityFocused":false,"bounds":{"bottom":300,"left":30,"right":1570,"top":181},"checkable":false,"checked":false,"className":"android.widget.EditText","clickable":true,"descendantCount":0,"dismissable":false,"editable":true,"enabled":true,"focusable":true,"focused":true,"invisibleToUser":false,"level":11,"longClickable":true,"packageName":"com.sina.weibo","password":false,"resourceId":"com.sina.weibo:id/edit_view","scrollable":false,"selected":false,"text":"你好"}],"className":"android.widget.RelativeLayout","clickable":false,"descendantCount":1,"dismissable":false,"editable":false,"enabled":true,"focusable":false,"focused":false,"invisibleToUser":false,"level":10,"longClickable":false,"packageName":"com.sina.weibo","password":false,"scrollable":false,"selected":false}],"className":"android.widget.RelativeLayout","clickable":false,"descendantCount":2,"dismissable":false,"editable":false,"enabled":true,"focusable":false,"focused":false,"invisibleToUser":false,"level":9,"longClickable":false,"packageName":"com.sina.weibo","password":false,"resourceId":"com.sina.weibo:id/element_editbox","scrollable":false,"selected":false},{"accessibilityFocused":false,"bounds":{"bottom":371,"left":0,"right":1600,"top":356},"checkable":false,"checked":false,"children":[{"accessibilityFocused":false,"bounds":{"bottom":356,"left":0,"right":1600,"top":356},"checkable":false,"checked":false,"className":"android.widget.RelativeLayout","clickable":false,"descendantCount":0,"dismissable":false,"editable":false,"enabled":true,"focusable":false,"focused":false,"invisibleToUser":true,"level":10,"longClickable":false,"packageName":"com.sina.weibo","password":false,"resourceId":"com.sina.weibo:id/unified_element_video","scrollable":false,"selected":false},{"accessibilityFocused":false,"bounds":{"bottom":371,"left":0,"right":1600,"top":370},"checkable":false,"checked":false,"className":"android.view.View","clickable":false,"descendantCount":0,"dismissable":false,"editable":false,"enabled":true,"focusable":false,"focused":false,"invisibleToUser":false,"level":10,"longClickable":false,"packageName":"com.sina.weibo","password":false,"resourceId":"com.sina.weibo:id/composer_pic_guide_empty","scrollable":false,"selected":false}],"className":"android.widget.LinearLayout","clickable":false,"descendantCount":2,"dismissable":false,"editable":false,"enabled":true,"focusable":false,"focused":false,"invisibleToUser":false,"level":9,"longClickable":false,"packageName":"com.sina.weibo","password":false,"resourceId":"com.sina.weibo:id/ll_addition_container","scrollable":false,"selected":false}],"className":"android.widget.LinearLayout","clickable":false,"descendantCount":6,"dismissable":false,"editable":false,"enabled":true,"focusable":false,"focused":false,"invisibleToUser":false,"level":8,"longClickable":false,"packageName":"com.sina.weibo","password":false,"scrollable":false,"selected":false}],"className":"android.widget.LinearLayout","clickable":false,"descendantCount":7,"dismissable":false,"editable":false,"enabled":true,"focusable":false,"focused":false,"invisibleToUser":false,"level":7,"longClickable":false,"packageName":"com.sina.weibo","password":false,"resourceId":"com.sina.weibo:id/element_container","scrollable":false,"selected":false}],"className":"android.widget.ScrollView","clickable":false,"descendantCount":8,"dismissable":false,"editable":false,"enabled":true,"focusable":true,"focused":false,"invisibleToUser":false,"level":6,"longClickable":false,"packageName":"com.sina.weibo","password":false,"resourceId":"com.sina.weibo:id/sv_element_container","scrollable":false,"selected":false},{"accessibilityFocused":false,"bounds":{"bottom":1731,"left":0,"right":1600,"top":1394},"checkable":false,"checked":false,"children":[{"accessibilityFocused":false,"bounds":{"bottom":1643,"left":0,"right":1600,"top":1394},"checkable":false,"checked":false,"children":[{"accessibilityFocused":false,"bounds":{"bottom":1643,"left":0,"right":1600,"top":1403},"checkable":false,"checked":false,"children":[{"accessibilityFocused":false,"bounds":{"bottom":1459,"left":0,"right":1600,"top":1403},"checkable":false,"checked":false,"children":[{"accessibilityFocused":false,"bounds":{"bottom":1459,"left":0,"right":1600,"top":1403},"checkable":false,"checked":false,"children":[{"accessibilityFocused":false,"bounds":{"bottom":1459,"left":0,"right":1560,"top":1403},"checkable":false,"checked":false,"children":[{"accessibilityFocused":false,"bounds":{"bottom":1459,"left":16,"right":200,"top":1403},"checkable":false,"checked":false,"children":[{"accessibilityFocused":false,"bounds":{"bottom":1451,"left":24,"right":64,"top":1411},"checkable":false,"checked":false,"className":"android.widget.ImageView","clickable":false,"descendantCount":0,"dismissable":false,"editable":false,"enabled":true,"focusable":false,"focused":false,"invisibleToUser":false,"level":13,"longClickable":false,"packageName":"com.sina.weibo","password":false,"resourceId":"com.sina.weibo:id/iv_icon","scrollable":false,"selected":false},{"accessibilityFocused":false,"bounds":{"bottom":1449,"left":64,"right":168,"top":1413},"checkable":false,"checked":false,"className":"android.widget.TextView","clickable":false,"descendantCount":0,"dismissable":false,"editable":false,"enabled":true,"focusable":false,"focused":false,"invisibleToUser":false,"level":13,"longClickable":false,"packageName":"com.sina.weibo","password":false,"resourceId":"com.sina.weibo:id/tv_text","scrollable":false,"selected":false,"text":"生活手记"},{"accessibilityFocused":false,"bounds":{"bottom":1443,"left":168,"right":192,"top":1419},"checkable":false,"checked":false,"className":"android.widget.ImageView","clickable":false,"descendantCount":0,"dismissable":false,"editable":false,"enabled":true,"focusable":false,"focused":false,"invisibleToUser":false,"level":13,"longClickable":false,"packageName":"com.sina.weibo","password":false,"resourceId":"com.sina.weibo:id/iv_more","scrollable":false,"selected":false}],"className":"android.view.ViewGroup","clickable":true,"collectionItemInfo":{"columnIndex":0,"columnSpan":1,"heading":false,"rowIndex":0,"rowSpan":1},"descendantCount":3,"dismissable":false,"editable":false,"enabled":true,"focusable":true,"focused":false,"invisibleToUser":false,"level":12,"longClickable":false,"packageName":"com.sina.weibo","password":false,"scrollable":false,"selected":false},{"accessibilityFocused":false,"bounds":{"bottom":1459,"left":216,"right":408,"top":1403},"checkable":false,"checked":false,"children":[{"accessibilityFocused":false,"bounds":{"bottom":1449,"left":228,"right":264,"top":1413},"checkable":false,"checked":false,"className":"android.widget.ImageView","clickable":false,"descendantCount":0,"dismissable":false,"editable":false,"enabled":true,"focusable":false,"focused":false,"invisibleToUser":false,"level":13,"longClickable":false,"packageName":"com.sina.weibo","password":false,"resourceId":"com.sina.weibo:id/iv_icon","scrollable":false,"selected":false},{"accessibilityFocused":false,"bounds":{"bottom":1449,"left":264,"right":388,"top":1413},"checkable":false,"checked":false,"className":"android.widget.TextView","clickable":false,"descendantCount":0,"dismissable":false,"editable":false,"enabled":true,"focusable":false,"focused":false,"invisibleToUser":false,"level":13,"longClickable":false,"packageName":"com.sina.weibo","password":false,"resourceId":"com.sina.weibo:id/tv_text","scrollable":false,"selected":false,"text":"NCT_WISH"}],"className":"android.view.ViewGroup","clickable":true,"collectionItemInfo":{"columnIndex":1,"columnSpan":1,"heading":false,"rowIndex":0,"rowSpan":1},"descendantCount":2,"dismissable":false,"editable":false,"enabled":true,"focusable":true,"focused":false,"invisibleToUser":false,"level":12,"longClickable":false,"packageName":"com.sina.weibo","password":false,"scrollable":false,"selected":false},{"accessibilityFocused":false,"bounds":{"bottom":1459,"left":424,"right":570,"top":1403},"checkable":false,"checked":false,"children":[{"accessibilityFocused":false,"bounds":{"bottom":1449,"left":436,"right":472,"top":1413},"checkable":false,"checked":false,"className":"android.widget.ImageView","clickable":false,"descendantCount":0,"dismissable":false,"editable":false,"enabled":true,"focusable":false,"focused":false,"invisibleToUser":false,"level":13,"longClickable":false,"packageName":"com.sina.weibo","password":false,"resourceId":"com.sina.weibo:id/iv_icon","scrollable":false,"selected":false},{"accessibilityFocused":false,"bounds":{"bottom":1449,"left":472,"right":550,"top":1413},"checkable":false,"checked":false,"className":"android.widget.TextView","clickable":false,"descendantCount":0,"dismissable":false,"editable":false,"enabled":true,"focusable":false,"focused":false,"invisibleToUser":false,"level":13,"longClickable":false,"packageName":"com.sina.weibo","password":false,"resourceId":"com.sina.weibo:id/tv_text","scrollable":false,"selected":false,"text":"朴志晟"}],"className":"android.view.ViewGroup","clickable":true,"collectionItemInfo":{"columnIndex":2,"columnSpan":1,"heading":false,"rowIndex":0,"rowSpan":1},"descendantCount":2,"dismissable":false,"editable":false,"enabled":true,"focusable":true,"focused":false,"invisibleToUser":false,"level":12,"longClickable":false,"packageName":"com.sina.weibo","password":false,"scrollable":false,"selected":false},{"accessibilityFocused":false,"bounds":{"bottom":1459,"left":586,"right":810,"top":1403},"checkable":false,"checked":false,"children":[{"accessibilityFocused":false,"bounds":{"bottom":1449,"left":598,"right":634,"top":1413},"checkable":false,"checked":false,"className":"android.widget.ImageView","clickable":false,"descendantCount":0,"dismissable":false,"editable":false,"enabled":true,"focusable":false,"focused":false,"invisibleToUser":false,"level":13,"longClickable":false,"packageName":"com.sina.weibo","password":false,"resourceId":"com.sina.weibo:id/iv_icon","scrollable":false,"selected":false},{"accessibilityFocused":false,"bounds":{"bottom":1449,"left":634,"right":790,"top":1413},"checkable":false,"checked":false,"className":"android.widget.TextView","clickable":false,"descendantCount":0,"dismissable":false,"editable":false,"enabled":true,"focusable":false,"focused":false,"invisibleToUser":false,"level":13,"longClickable":false,"packageName":"com.sina.weibo","password":false,"resourceId":"com.sina.weibo:id/tv_text","scrollable":false,"selected":false,"text":"星游记第一季"}],"className":"android.view.ViewGroup","clickable":true,"collectionItemInfo":{"columnIndex":3,"columnSpan":1,"heading":false,"rowIndex":0,"rowSpan":1},"descendantCount":2,"dismissable":false,"editable":false,"enabled":true,"focusable":true,"focused":false,"invisibleToUser":false,"level":12,"longClickable":false,"packageName":"com.sina.weibo","password":false,"scrollable":false,"selected":false},{"accessibilityFocused":false,"bounds":{"bottom":1459,"left":826,"right":1050,"top":1403},"checkable":false,"checked":false,"children":[{"accessibilityFocused":false,"bounds":{"bottom":1449,"left":838,"right":874,"top":1413},"checkable":false,"checked":false,"className":"android.widget.ImageView","clickable":false,"descendantCount":0,"dismissable":false,"editable":false,"enabled":true,"focusable":false,"focused":false,"invisibleToUser":false,"level":13,"longClickable":false,"packageName":"com.sina.weibo","password":false,"resourceId":"com.sina.weibo:id/iv_icon","scrollable":false,"selected":false},{"accessibilityFocused":false,"bounds":{"bottom":1449,"left":874,"right":1030,"top":1413},"checkable":false,"checked":false,"className":"android.widget.TextView","clickable":false,"descendantCount":0,"dismissable":false,"editable":false,"enabled":true,"focusable":false,"focused":false,"invisibleToUser":false,"level":13,"longClickable":false,"packageName":"com.sina.weibo","password":false,"resourceId":"com.sina.weibo:id/tv_text","scrollable":false,"selected":false,"text":"栗小葵便利店"}],"className":"android.view.ViewGroup","clickable":true,"collectionItemInfo":{"columnIndex":4,"columnSpan":1,"heading":false,"rowIndex":0,"rowSpan":1},"descendantCount":2,"dismissable":false,"editable":false,"enabled":true,"focusable":true,"focused":false,"invisibleToUser":false,"level":12,"longClickable":false,"packageName":"com.sina.weibo","password":false,"scrollable":false,"selected":false},{"accessibilityFocused":false,"bounds":{"bottom":1459,"left":1066,"right":1212,"top":1403},"checkable":false,"checked":false,"children":[{"accessibilityFocused":false,"bounds":{"bottom":1449,"left":1078,"right":1114,"top":1413},"checkable":false,"checked":false,"className":"android.widget.ImageView","clickable":false,"descendantCount":0,"dismissable":false,"editable":false,"enabled":true,"focusable":false,"focused":false,"invisibleToUser":false,"level":13,"longClickable":false,"packageName":"com.sina.weibo","password":false,"resourceId":"com.sina.weibo:id/iv_icon","scrollable":false,"selected":false},{"accessibilityFocused":false,"bounds":{"bottom":1449,"left":1114,"right":1192,"top":1413},"checkable":false,"checked":false,"className":"android.widget.TextView","clickable":false,"descendantCount":0,"dismissable":false,"editable":false,"enabled":true,"focusable":false,"focused":false,"invisibleToUser":false,"level":13,"longClickable":false,"packageName":"com.sina.weibo","password":false,"resourceId":"com.sina.weibo:id/tv_text","scrollable":false,"selected":false,"text":"cv瀚墨"}],"className":"android.view.ViewGroup","clickable":true,"collectionItemInfo":{"columnIndex":5,"columnSpan":1,"heading":false,"rowIndex":0,"rowSpan":1},"descendantCount":2,"dismissable":false,"editable":false,"enabled":true,"focusable":true,"focused":false,"invisibleToUser":false,"level":12,"longClickable":false,"packageName":"com.sina.weibo","password":false,"scrollable":false,"selected":false},{"accessibilityFocused":false,"bounds":{"bottom":1459,"left":1228,"right":1400,"top":1403},"checkable":false,"checked":false,"children":[{"accessibilityFocused":false,"bounds":{"bottom":1449,"left":1240,"right":1276,"top":1413},"checkable":false,"checked":false,"className":"android.widget.ImageView","clickable":false,"descendantCount":0,"dismissable":false,"editable":false,"enabled":true,"focusable":false,"focused":false,"invisibleToUser":false,"level":13,"longClickable":false,"packageName":"com.sina.weibo","password":false,"resourceId":"com.sina.weibo:id/iv_icon","scrollable":false,"selected":false},{"accessibilityFocused":false,"bounds":{"bottom":1449,"left":1276,"right":1380,"top":1413},"checkable":false,"checked":false,"className":"android.widget.TextView","clickable":false,"descendantCount":0,"dismissable":false,"editable":false,"enabled":true,"focusable":false,"focused":false,"invisibleToUser":false,"level":13,"longClickable":false,"packageName":"com.sina.weibo","password":false,"resourceId":"com.sina.weibo:id/tv_text","scrollable":false,"selected":false,"text":"雄狮少年"}],"className":"android.view.ViewGroup","clickable":true,"collectionItemInfo":{"columnIndex":6,"columnSpan":1,"heading":false,"rowIndex":0,"rowSpan":1},"descendantCount":2,"dismissable":false,"editable":false,"enabled":true,"focusable":true,"focused":false,"invisibleToUser":false,"level":12,"longClickable":false,"packageName":"com.sina.weibo","password":false,"scrollable":false,"selected":false},{"accessibilityFocused":false,"bounds":{"bottom":1459,"left":1416,"right":1560,"top":1403},"checkable":false,"checked":false,"children":[{"accessibilityFocused":false,"bounds":{"bottom":1449,"left":1428,"right":1464,"top":1413},"checkable":false,"checked":false,"className":"android.widget.ImageView","clickable":false,"descendantCount":0,"dismissable":false,"editable":false,"enabled":true,"focusable":false,"focused":false,"invisibleToUser":false,"level":13,"longClickable":false,"packageName":"com.sina.weibo","password":false,"resourceId":"com.sina.weibo:id/iv_icon","scrollable":false,"selected":false},{"accessibilityFocused":false,"bounds":{"bottom":1449,"left":1464,"right":1542,"top":1413},"checkable":false,"checked":false,"className":"android.widget.TextView","clickable":false,"descendantCount":0,"dismissable":false,"editable":false,"enabled":true,"focusable":false,"focused":false,"invisibleToUser":false,"level":13,"longClickable":false,"packageName":"com.sina.weibo","password":false,"resourceId":"com.sina.weibo:id/tv_text","scrollable":false,"selected":false,"text":"吴宣仪"}],"className":"android.view.ViewGroup","clickable":true,"collectionItemInfo":{"columnIndex":7,"columnSpan":1,"heading":false,"rowIndex":0,"rowSpan":1},"descendantCount":2,"dismissable":false,"editable":false,"enabled":true,"focusable":true,"focused":false,"invisibleToUser":false,"level":12,"longClickable":false,"packageName":"com.sina.weibo","password":false,"scrollable":false,"selected":false}],"className":"androidx.recyclerview.widget.RecyclerView","clickable":false,"collectionInfo":{"columnCount":11,"hierarchical":false,"rowCount":1,"selectionMode":0},"descendantCount":25,"dismissable":false,"editable":false,"enabled":true,"focusable":true,"focused":false,"invisibleToUser":false,"level":11,"longClickable":false,"packageName":"com.sina.weibo","password":false,"scrollable":true,"selected":false},{"accessibilityFocused":false,"bounds":{"bottom":1459,"left":1524,"right":1600,"top":1403},"checkable":false,"checked":false,"className":"android.widget.ImageView","clickable":true,"descendantCount":0,"dismissable":false,"editable":false,"enabled":true,"focusable":true,"focused":false,"invisibleToUser":false,"level":11,"longClickable":false,"packageName":"com.sina.weibo","password":false,"scrollable":false,"selected":false}],"className":"android.widget.RelativeLayout","clickable":false,"descendantCount":27,"dismissable":false,"editable":false,"enabled":true,"focusable":false,"focused":false,"invisibleToUser":false,"level":10,"longClickable":false,"packageName":"com.sina.weibo","password":false,"resourceId":"com.sina.weibo:id/hot_subject_guide_element_view","scrollable":false,"selected":false}],"className":"android.view.ViewGroup","clickable":false,"descendantCount":28,"dismissable":false,"editable":false,"enabled":true,"focusable":false,"focused":false,"invisibleToUser":false,"level":9,"longClickable":false,"packageName":"com.sina.weibo","password":false,"resourceId":"com.sina.weibo:id/activity_fixed_elements","scrollable":false,"selected":false},{"accessibilityFocused":false,"bounds":{"bottom":1549,"left":0,"right":1600,"top":1465},"checkable":false,"checked":false,"children":[{"accessibilityFocused":false,"bounds":{"bottom":1535,"left":16,"right":186,"top":1479},"checkable":false,"checked":false,"children":[{"accessibilityFocused":false,"bounds":{"bottom":1535,"left":16,"right":186,"top":1479},"checkable":false,"checked":false,"children":[{"accessibilityFocused":false,"bounds":{"bottom":1535,"left":16,"right":186,"top":1479},"checkable":false,"checked":false,"children":[{"accessibilityFocused":false,"bounds":{"bottom":1535,"left":16,"right":186,"top":1479},"checkable":false,"checked":false,"children":[{"accessibilityFocused":false,"bounds":{"bottom":1527,"left":24,"right":64,"top":1487},"checkable":false,"checked":false,"className":"android.widget.ImageView","clickable":false,"descendantCount":0,"dismissable":false,"editable":false,"enabled":true,"focusable":false,"focused":false,"invisibleToUser":false,"level":14,"longClickable":false,"packageName":"com.sina.weibo","password":false,"resourceId":"com.sina.weibo:id/tv_location_imageivew","scrollable":false,"selected":false},{"accessibilityFocused":false,"bounds":{"bottom":1521,"left":70,"right":186,"top":1493},"checkable":false,"checked":false,"className":"android.widget.TextView","clickable":false,"descendantCount":0,"dismissable":false,"editable":false,"enabled":true,"focusable":false,"focused":false,"invisibleToUser":false,"level":14,"longClickable":false,"packageName":"com.sina.weibo","password":false,"resourceId":"com.sina.weibo:id/tv_location","scrollable":false,"selected":false,"text":"添加位置"}],"className":"android.widget.LinearLayout","clickable":true,"descendantCount":2,"dismissable":false,"editable":false,"enabled":true,"focusable":true,"focused":false,"invisibleToUser":false,"level":13,"longClickable":false,"packageName":"com.sina.weibo","password":false,"resourceId":"com.sina.weibo:id/tv_location_ly","scrollable":false,"selected":false}],"className":"android.widget.LinearLayout","clickable":true,"descendantCount":3,"dismissable":false,"editable":false,"enabled":true,"focusable":true,"focused":false,"invisibleToUser":false,"level":12,"longClickable":false,"packageName":"com.sina.weibo","password":false,"resourceId":"com.sina.weibo:id/ly_poi","scrollable":false,"selected":false}],"className":"android.widget.RelativeLayout","clickable":false,"descendantCount":4,"dismissable":false,"editable":false,"enabled":true,"focusable":false,"focused":false,"invisibleToUser":false,"level":11,"longClickable":false,"packageName":"com.sina.weibo","password":false,"scrollable":false,"selected":false}],"className":"android.widget.RelativeLayout","clickable":false,"descendantCount":5,"dismissable":false,"editable":false,"enabled":true,"focusable":false,"focused":false,"invisibleToUser":false,"level":10,"longClickable":false,"packageName":"com.sina.weibo","password":false,"resourceId":"com.sina.weibo:id/element_location","scrollable":false,"selected":false},{"accessibilityFocused":false,"bounds":{"bottom":1535,"left":202,"right":324,"top":1479},"checkable":false,"checked":false,"children":[{"accessibilityFocused":false,"bounds":{"bottom":1535,"left":202,"right":324,"top":1479},"checkable":false,"checked":false,"children":[{"accessibilityFocused":false,"bounds":{"bottom":1535,"left":202,"right":324,"top":1479},"checkable":false,"checked":false,"children":[{"accessibilityFocused":false,"bounds":{"bottom":1527,"left":210,"right":250,"top":1487},"checkable":false,"checked":false,"className":"android.widget.ImageView","clickable":false,"descendantCount":0,"dismissable":false,"editable":false,"enabled":true,"focusable":false,"focused":false,"invisibleToUser":false,"level":13,"longClickable":false,"packageName":"com.sina.weibo","password":false,"resourceId":"com.sina.weibo:id/iv_icon","scrollable":false,"selected":false},{"accessibilityFocused":false,"bounds":{"bottom":1521,"left":256,"right":324,"top":1493},"checkable":false,"checked":false,"className":"android.widget.TextView","clickable":false,"descendantCount":0,"dismissable":false,"editable":false,"enabled":true,"focusable":false,"focused":false,"invisibleToUser":false,"level":13,"longClickable":false,"packageName":"com.sina.weibo","password":false,"resourceId":"com.sina.weibo:id/tv_text","scrollable":false,"selected":false,"text":"超话"}],"className":"android.widget.LinearLayout","clickable":true,"descendantCount":2,"dismissable":false,"editable":false,"enabled":true,"focusable":true,"focused":false,"invisibleToUser":false,"level":12,"longClickable":false,"packageName":"com.sina.weibo","password":false,"resourceId":"com.sina.weibo:id/ll_layout_view","scrollable":false,"selected":false}],"className":"android.widget.RelativeLayout","clickable":false,"descendantCount":3,"dismissable":false,"editable":false,"enabled":true,"focusable":false,"focused":false,"invisibleToUser":false,"level":11,"longClickable":false,"packageName":"com.sina.weibo","password":false,"scrollable":false,"selected":false}],"className":"android.widget.RelativeLayout","clickable":false,"descendantCount":4,"dismissable":false,"editable":false,"enabled":true,"focusable":false,"focused":false,"invisibleToUser":false,"level":10,"longClickable":false,"packageName":"com.sina.weibo","password":false,"resourceId":"com.sina.weibo:id/element_super_topic","scrollable":false,"selected":false},{"accessibilityFocused":false,"bounds":{"bottom":1527,"left":1433,"right":1450,"top":1486},"checkable":false,"checked":false,"className":"android.widget.TextView","clickable":true,"contentDescription":"可输入字数：","descendantCount":0,"dismissable":false,"editable":false,"enabled":true,"focusable":true,"focused":false,"invisibleToUser":false,"level":10,"longClickable":false,"packageName":"com.sina.weibo","password":false,"resourceId":"com.sina.weibo:id/input_limit","scrollable":false,"selected":false,"text":"2"},{"accessibilityFocused":false,"bounds":{"bottom":1535,"left":1470,"right":1584,"top":1479},"checkable":false,"checked":false,"children":[{"accessibilityFocused":false,"bounds":{"bottom":1535,"left":1470,"right":1584,"top":1479},"checkable":false,"checked":false,"children":[{"accessibilityFocused":false,"bounds":{"bottom":1535,"left":1470,"right":1584,"top":1479},"checkable":false,"checked":false,"children":[{"accessibilityFocused":false,"bounds":{"bottom":1527,"left":1478,"right":1518,"top":1487},"checkable":false,"checked":false,"className":"android.widget.ImageView","clickable":true,"descendantCount":0,"dismissable":false,"editable":false,"enabled":true,"focusable":true,"focused":false,"invisibleToUser":false,"level":13,"longClickable":false,"packageName":"com.sina.weibo","password":false,"resourceId":"com.sina.weibo:id/ib_meyou","scrollable":false,"selected":false},{"accessibilityFocused":false,"bounds":{"bottom":1521,"left":1520,"right":1568,"top":1493},"checkable":false,"checked":false,"className":"android.widget.TextView","clickable":false,"descendantCount":0,"dismissable":false,"editable":false,"enabled":true,"focusable":false,"focused":false,"invisibleToUser":false,"level":13,"longClickable":false,"packageName":"com.sina.weibo","password":false,"resourceId":"com.sina.weibo:id/ib_meyou_tv","scrollable":false,"selected":false,"text":"公开"}],"className":"android.widget.LinearLayout","clickable":true,"contentDescription":"密友","descendantCount":2,"dismissable":false,"editable":false,"enabled":true,"focusable":true,"focused":false,"invisibleToUser":false,"level":12,"longClickable":false,"packageName":"com.sina.weibo","password":false,"resourceId":"com.sina.weibo:id/ib_meyou_ll","scrollable":false,"selected":false}],"className":"android.widget.RelativeLayout","clickable":false,"descendantCount":3,"dismissable":false,"editable":false,"enabled":true,"focusable":false,"focused":false,"invisibleToUser":false,"level":11,"longClickable":false,"packageName":"com.sina.weibo","password":false,"resourceId":"com.sina.weibo:id/element_group","scrollable":false,"selected":false}],"className":"android.widget.FrameLayout","clickable":false,"descendantCount":4,"dismissable":false,"editable":false,"enabled":true,"focusable":false,"focused":false,"invisibleToUser":false,"level":10,"longClickable":false,"packageName":"com.sina.weibo","password":false,"resourceId":"com.sina.weibo:id/element_group_wrapper","scrollable":false,"selected":false}],"className":"android.widget.RelativeLayout","clickable":false,"descendantCount":17,"dismissable":false,"editable":false,"enabled":true,"focusable":false,"focused":false,"invisibleToUser":false,"level":9,"longClickable":false,"packageName":"com.sina.weibo","password":false,"resourceId":"com.sina.weibo:id/loction_and_group","scrollable":false,"selected":false},{"accessibilityFocused":false,"bounds":{"bottom":1643,"left":0,"right":1600,"top":1543},"checkable":false,"checked":false,"children":[{"accessibilityFocused":false,"bounds":{"bottom":1643,"left":0,"right":1600,"top":1543},"checkable":false,"checked":false,"children":[{"accessibilityFocused":false,"bounds":{"bottom":1640,"left":0,"right":1600,"top":1560},"checkable":false,"checked":false,"children":[{"accessibilityFocused":false,"bounds":{"bottom":1640,"left":0,"right":1319,"top":1560},"checkable":false,"checked":false,"children":[{"accessibilityFocused":false,"bounds":{"bottom":1628,"left":0,"right":160,"top":1572},"checkable":false,"checked":false,"children":[{"accessibilityFocused":false,"bounds":{"bottom":1628,"left":16,"right":160,"top":1572},"checkable":false,"checked":false,"className":"android.widget.TextView","clickable":true,"descendantCount":0,"dismissable":false,"editable":false,"enabled":true,"focusable":true,"focused":false,"invisibleToUser":false,"level":14,"longClickable":false,"packageName":"com.sina.weibo","password":false,"resourceId":"com.sina.weibo:id/location_detail_btn","scrollable":false,"selected":false,"text":"清华大学"}],"className":"android.widget.LinearLayout","clickable":false,"descendantCount":1,"dismissable":false,"editable":false,"enabled":true,"focusable":false,"focused":false,"invisibleToUser":false,"level":13,"longClickable":false,"packageName":"com.sina.weibo","password":false,"scrollable":false,"selected":false},{"accessibilityFocused":false,"bounds":{"bottom":1628,"left":160,"right":268,"top":1572},"checkable":false,"checked":false,"children":[{"accessibilityFocused":false,"bounds":{"bottom":1628,"left":176,"right":268,"top":1572},"checkable":false,"checked":false,"className":"android.widget.TextView","clickable":true,"descendantCount":0,"dismissable":false,"editable":false,"enabled":true,"focusable":true,"focused":false,"invisibleToUser":false,"level":14,"longClickable":false,"packageName":"com.sina.weibo","password":false,"resourceId":"com.sina.weibo:id/location_detail_btn","scrollable":false,"selected":false,"text":"北京"}],"className":"android.widget.LinearLayout","clickable":false,"descendantCount":1,"dismissable":false,"editable":false,"enabled":true,"focusable":false,"focused":false,"invisibleToUser":false,"level":13,"longClickable":false,"packageName":"com.sina.weibo","password":false,"scrollable":false,"selected":false},{"accessibilityFocused":false,"bounds":{"bottom":1628,"left":268,"right":558,"top":1572},"checkable":false,"checked":false,"children":[{"accessibilityFocused":false,"bounds":{"bottom":1628,"left":284,"right":558,"top":1572},"checkable":false,"checked":false,"className":"android.widget.TextView","clickable":true,"descendantCount":0,"dismissable":false,"editable":false,"enabled":true,"focusable":true,"focused":false,"invisibleToUser":false,"level":14,"longClickable":false,"packageName":"com.sina.weibo","password":false,"resourceId":"com.sina.weibo:id/location_detail_btn","scrollable":false,"selected":false,"text":"清华大学紫荆园餐厅"}],"className":"android.widget.LinearLayout","clickable":false,"descendantCount":1,"dismissable":false,"editable":false,"enabled":true,"focusable":false,"focused":false,"invisibleToUser":false,"level":13,"longClickable":false,"packageName":"com.sina.weibo","password":false,"scrollable":false,"selected":false},{"accessibilityFocused":false,"bounds":{"bottom":1628,"left":558,"right":861,"top":1572},"checkable":false,"checked":false,"children":[{"accessibilityFocused":false,"bounds":{"bottom":1628,"left":574,"right":861,"top":1572},"checkable":false,"checked":false,"className":"android.widget.TextView","clickable":true,"descendantCount":0,"dismissable":false,"editable":false,"enabled":true,"focusable":true,"focused":false,"invisibleToUser":false,"level":14,"longClickable":false,"packageName":"com.sina.weibo","password":false,"resourceId":"com.sina.weibo:id/location_detail_btn","scrollable":false,"selected":false,"text":"清华大学-桃李园餐厅"}],"className":"android.widget.LinearLayout","clickable":false,"descendantCount":1,"dismissable":false,"editable":false,"enabled":true,"focusable":false,"focused":false,"invisibleToUser":false,"level":13,"longClickable":false,"packageName":"com.sina.weibo","password":false,"scrollable":false,"selected":false},{"accessibilityFocused":false,"bounds":{"bottom":1628,"left":861,"right":1195,"top":1572},"checkable":false,"checked":false,"children":[{"accessibilityFocused":false,"bounds":{"bottom":1628,"left":877,"right":1195,"top":1572},"checkable":false,"checked":false,"className":"android.widget.TextView","clickable":true,"descendantCount":0,"dismissable":false,"editable":false,"enabled":true,"focusable":true,"focused":false,"invisibleToUser":false,"level":14,"longClickable":false,"packageName":"com.sina.weibo","password":false,"resourceId":"com.sina.weibo:id/location_detail_btn","scrollable":false,"selected":false,"text":"清华大学桃李园简约餐..."}],"className":"android.widget.LinearLayout","clickable":false,"descendantCount":1,"dismissable":false,"editable":false,"enabled":true,"focusable":false,"focused":false,"invisibleToUser":false,"level":13,"longClickable":false,"packageName":"com.sina.weibo","password":false,"scrollable":false,"selected":false},{"accessibilityFocused":false,"bounds":{"bottom":1628,"left":1195,"right":1319,"top":1572},"checkable":false,"checked":false,"children":[{"accessibilityFocused":false,"bounds":{"bottom":1628,"left":1211,"right":1303,"top":1572},"checkable":false,"checked":false,"className":"android.widget.TextView","clickable":true,"descendantCount":0,"dismissable":false,"editable":false,"enabled":true,"focusable":true,"focused":false,"invisibleToUser":false,"level":14,"longClickable":false,"packageName":"com.sina.weibo","password":false,"resourceId":"com.sina.weibo:id/location_detail_btn","scrollable":false,"selected":false,"text":"更多"}],"className":"android.widget.LinearLayout","clickable":false,"descendantCount":1,"dismissable":false,"editable":false,"enabled":true,"focusable":false,"focused":false,"invisibleToUser":false,"level":13,"longClickable":false,"packageName":"com.sina.weibo","password":false,"scrollable":false,"selected":false}],"className":"android.widget.LinearLayout","clickable":false,"descendantCount":12,"dismissable":false,"editable":false,"enabled":true,"focusable":false,"focused":false,"invisibleToUser":false,"level":12,"longClickable":false,"packageName":"com.sina.weibo","password":false,"resourceId":"com.sina.weibo:id/scroll_linearlayout","scrollable":false,"selected":false}],"className":"android.widget.HorizontalScrollView","clickable":false,"descendantCount":13,"dismissable":false,"editable":false,"enabled":true,"focusable":true,"focused":false,"invisibleToUser":false,"level":11,"longClickable":false,"packageName":"com.sina.weibo","password":false,"scrollable":false,"selected":false},{"accessibilityFocused":false,"bounds":{"bottom":1640,"left":1524,"right":1600,"top":1560},"checkable":false,"checked":false,"children":[{"accessibilityFocused":false,"bounds":{"bottom":1638,"left":1524,"right":1600,"top":1562},"checkable":false,"checked":false,"className":"android.widget.ImageButton","clickable":false,"descendantCount":0,"dismissable":false,"editable":false,"enabled":true,"focusable":true,"focused":false,"invisibleToUser":false,"level":12,"longClickable":false,"packageName":"com.sina.weibo","password":false,"scrollable":false,"selected":false}],"className":"android.widget.RelativeLayout","clickable":true,"descendantCount":1,"dismissable":false,"editable":false,"enabled":true,"focusable":true,"focused":false,"invisibleToUser":false,"level":11,"longClickable":false,"packageName":"com.sina.weibo","password":false,"resourceId":"com.sina.weibo:id/delete_pic_recommend_loaction","scrollable":false,"selected":false}],"className":"android.widget.RelativeLayout","clickable":false,"descendantCount":16,"dismissable":false,"editable":false,"enabled":true,"focusable":false,"focused":false,"invisibleToUser":false,"level":10,"longClickable":false,"packageName":"com.sina.weibo","password":false,"resourceId":"com.sina.weibo:id/photo_location_scroll_view","scrollable":false,"selected":false}],"className":"android.widget.RelativeLayout","clickable":false,"descendantCount":17,"dismissable":false,"editable":false,"enabled":true,"focusable":false,"focused":false,"invisibleToUser":false,"level":9,"longClickable":false,"packageName":"com.sina.weibo","password":false,"resourceId":"com.sina.weibo:id/photo_loction_scroll_view","scrollable":false,"selected":false}],"className":"android.widget.RelativeLayout","clickable":false,"descendantCount":65,"dismissable":false,"editable":false,"enabled":true,"focusable":false,"focused":false,"invisibleToUser":false,"level":8,"longClickable":false,"packageName":"com.sina.weibo","password":false,"resourceId":"com.sina.weibo:id/composer_fix_view","scrollable":false,"selected":false}],"className":"android.widget.RelativeLayout","clickable":false,"descendantCount":66,"dismissable":false,"editable":false,"enabled":true,"focusable":false,"focused":false,"invisibleToUser":false,"level":7,"longClickable":false,"packageName":"com.sina.weibo","password":false,"resourceId":"com.sina.weibo:id/fixed_element_container","scrollable":false,"selected":false},{"accessibilityFocused":false,"bounds":{"bottom":1731,"left":0,"right":1600,"top":1643},"checkable":false,"checked":false,"children":[{"accessibilityFocused":false,"bounds":{"bottom":1731,"left":0,"right":1600,"top":1643},"checkable":false,"checked":false,"children":[{"accessibilityFocused":false,"bounds":{"bottom":1731,"left":0,"right":1600,"top":1643},"checkable":false,"checked":false,"children":[{"accessibilityFocused":false,"bounds":{"bottom":1731,"left":0,"right":266,"top":1643},"checkable":false,"checked":false,"children":[{"accessibilityFocused":false,"bounds":{"bottom":1711,"left":109,"right":157,"top":1663},"checkable":false,"checked":false,"className":"android.widget.ImageButton","clickable":false,"contentDescription":"插入图片","descendantCount":0,"dismissable":false,"editable":false,"enabled":true,"focusable":true,"focused":false,"invisibleToUser":false,"level":11,"longClickable":false,"packageName":"com.sina.weibo","password":false,"resourceId":"com.sina.weibo:id/ib_insert_pics","scrollable":false,"selected":false}],"className":"android.widget.RelativeLayout","clickable":true,"descendantCount":1,"dismissable":false,"editable":false,"enabled":true,"focusable":true,"focused":false,"invisibleToUser":false,"level":10,"longClickable":true,"packageName":"com.sina.weibo","password":false,"resourceId":"com.sina.weibo:id/rl_insert_pics","scrollable":false,"selected":false},{"accessibilityFocused":false,"bounds":{"bottom":1731,"left":266,"right":532,"top":1643},"checkable":false,"checked":false,"className":"android.widget.ImageButton","clickable":true,"contentDescription":"搜索","descendantCount":0,"dismissable":false,"editable":false,"enabled":true,"focusable":true,"focused":false,"invisibleToUser":false,"level":10,"longClickable":false,"packageName":"com.sina.weibo","password":false,"resourceId":"com.sina.weibo:id/ib_insert_at","scrollable":false,"selected":false},{"accessibilityFocused":false,"bounds":{"bottom":1731,"left":532,"right":799,"top":1643},"checkable":false,"checked":false,"className":"android.widget.ImageButton","clickable":true,"contentDescription":"话题、电影、书、歌曲、地点、股票","descendantCount":0,"dismissable":false,"editable":false,"enabled":true,"focusable":true,"focused":false,"invisibleToUser":false,"level":10,"longClickable":false,"packageName":"com.sina.weibo","password":false,"resourceId":"com.sina.weibo:id/ib_insert_topic","scrollable":false,"selected":false},{"accessibilityFocused":false,"bounds":{"bottom":1731,"left":799,"right":1066,"top":1643},"checkable":false,"checked":false,"className":"android.widget.ImageButton","clickable":true,"contentDescription":"话题、电影、书、歌曲、地点、股票","descendantCount":0,"dismissable":false,"editable":false,"enabled":true,"focusable":true,"focused":false,"invisibleToUser":false,"level":10,"longClickable":false,"packageName":"com.sina.weibo","password":false,"resourceId":"com.sina.weibo:id/composer_insert_gif","scrollable":false,"selected":false},{"accessibilityFocused":false,"bounds":{"bottom":1731,"left":1066,"right":1333,"top":1643},"checkable":false,"checked":false,"className":"android.widget.ImageButton","clickable":true,"contentDescription":"请插入表情","descendantCount":0,"dismissable":false,"editable":false,"enabled":true,"focusable":true,"focused":false,"invisibleToUser":false,"level":10,"longClickable":false,"packageName":"com.sina.weibo","password":false,"resourceId":"com.sina.weibo:id/ib_face_keyboard","scrollable":false,"selected":false},{"accessibilityFocused":false,"bounds":{"bottom":1731,"left":1333,"right":1600,"top":1643},"checkable":false,"checked":false,"className":"android.widget.ImageButton","clickable":true,"contentDescription":"更多操作","descendantCount":0,"dismissable":false,"editable":false,"enabled":true,"focusable":true,"focused":false,"invisibleToUser":false,"level":10,"longClickable":false,"packageName":"com.sina.weibo","password":false,"resourceId":"com.sina.weibo:id/ib_add_app","scrollable":false,"selected":false}],"className":"android.widget.LinearLayout","clickable":false,"descendantCount":7,"dismissable":false,"editable":false,"enabled":true,"focusable":false,"focused":false,"invisibleToUser":false,"level":9,"longClickable":false,"packageName":"com.sina.weibo","password":false,"scrollable":false,"selected":false}],"className":"android.widget.LinearLayout","clickable":false,"descendantCount":8,"dismissable":false,"editable":false,"enabled":true,"focusable":false,"focused":false,"invisibleToUser":false,"level":8,"longClickable":false,"packageName":"com.sina.weibo","password":false,"resourceId":"com.sina.weibo:id/toolbar","scrollable":false,"selected":false}],"className":"android.widget.LinearLayout","clickable":false,"descendantCount":9,"dismissable":false,"editable":false,"enabled":true,"focusable":false,"focused":false,"invisibleToUser":false,"level":7,"longClickable":false,"packageName":"com.sina.weibo","password":false,"resourceId":"com.sina.weibo:id/toolbar_panel","scrollable":false,"selected":false}],"className":"android.widget.LinearLayout","clickable":false,"descendantCount":77,"dismissable":false,"editable":false,"enabled":true,"focusable":false,"focused":false,"invisibleToUser":false,"level":6,"longClickable":false,"packageName":"com.sina.weibo","password":false,"resourceId":"com.sina.weibo:id/bottom_container","scrollable":false,"selected":false}],"className":"android.widget.RelativeLayout","clickable":false,"descendantCount":87,"dismissable":false,"editable":false,"enabled":true,"focusable":false,"focused":false,"invisibleToUser":false,"level":5,"longClickable":false,"packageName":"com.sina.weibo","password":false,"scrollable":false,"selected":false}],"className":"android.widget.FrameLayout","clickable":false,"descendantCount":89,"dismissable":false,"editable":false,"enabled":true,"focusable":false,"focused":false,"invisibleToUser":false,"level":4,"longClickable":false,"packageName":"com.sina.weibo","password":false,"resourceId":"com.sina.weibo:id/rootview","scrollable":false,"selected":false},{"accessibilityFocused":false,"bounds":{"bottom":152,"left":0,"right":1600,"top":151},"checkable":false,"checked":false,"className":"android.widget.ImageView","clickable":false,"descendantCount":0,"dismissable":false,"editable":false,"enabled":true,"focusable":false,"focused":false,"invisibleToUser":false,"level":4,"longClickable":false,"packageName":"com.sina.weibo","password":false,"scrollable":false,"selected":false}],"className":"android.widget.RelativeLayout","clickable":false,"descendantCount":106,"dismissable":false,"editable":false,"enabled":true,"focusable":false,"focused":false,"invisibleToUser":false,"level":3,"longClickable":false,"packageName":"com.sina.weibo","password":false,"scrollable":false,"selected":false}],"className":"android.widget.FrameLayout","clickable":false,"descendantCount":108,"dismissable":false,"editable":false,"enabled":true,"focusable":false,"focused":false,"invisibleToUser":false,"level":2,"longClickable":false,"packageName":"com.sina.weibo","password":false,"resourceId":"android:id/content","scrollable":false,"selected":false}],"className":"android.widget.LinearLayout","clickable":false,"descendantCount":109,"dismissable":false,"editable":false,"enabled":true,"focusable":false,"focused":false,"invisibleToUser":false,"level":1,"longClickable":false,"packageName":"com.sina.weibo","password":false,"scrollable":false,"selected":false}],"className":"android.widget.FrameLayout","clickable":false,"descendantCount":110,"dismissable":false,"editable":false,"enabled":true,"focusable":false,"focused":false,"invisibleToUser":false,"level":0,"longClickable":false,"packageName":"com.sina.weibo","password":false,"scrollable":false,"selected":false}